agent_roi/__init__.py
agent_roi/audit/__init__.py
agent_roi/audit/event.py
agent_roi/audit/store.py
agent_roi/cli/__init__.py
agent_roi/cli/sentinel.py
agent_roi/control/__init__.py
agent_roi/control/decision.py
agent_roi/control/guardrails.py
agent_roi/finops/__init__.py
agent_roi/finops/analyzer.py
agent_roi/policies/__init__.py
agent_roi/policies/finops_policy.yaml
agent_roi/policies/loader.py
agent_roi/policies/procurement_policy.yaml
agent_roi/policies/validate.py
agent_roi/procurement/__init__.py
agent_roi/procurement/analyzer.py
agent_roi/roi/__init__.py
agent_roi/roi/executive.py
agent_roi/roi/report.py
agent_roi/runtime/__init__.py
agent_roi/runtime/artifacts.py
agent_roi/runtime/context.py
agent_roi/runtime/executor.py
agent_roi-0.1.4.dist-info/METADATA
agent_roi-0.1.4.dist-info/WHEEL
agent_roi-0.1.4.dist-info/entry_points.txt
agent_roi-0.1.4.dist-info/licenses/LICENSE
agent_roi-0.1.4.dist-info/RECORD
