Metadata-Version: 2.4
Name: agent-roi
Version: 0.1.4
Summary: Production control plane for agentic AI: guardrails, confidence decisioning, immutable audit logging
Author: Tarek
License: MIT License
License-File: LICENSE
Requires-Python: >=3.10
Requires-Dist: pyyaml>=6.0
Provides-Extra: dev
Requires-Dist: pytest>=7.0; extra == 'dev'
